MANIFEST.in
setup.cfg
setup.py
Products/__init__.py
Products.PloneBooking.egg-info/PKG-INFO
Products.PloneBooking.egg-info/SOURCES.txt
Products.PloneBooking.egg-info/dependency_links.txt
Products.PloneBooking.egg-info/entry_points.txt
Products.PloneBooking.egg-info/namespace_packages.txt
Products.PloneBooking.egg-info/not-zip-safe
Products.PloneBooking.egg-info/requires.txt
Products.PloneBooking.egg-info/top_level.txt
Products/PloneBooking/ABOUT
Products/PloneBooking/BookingPermissions.py
Products/PloneBooking/BookingTool.py
Products/PloneBooking/CHANGES
Products/PloneBooking/DateManager.py
Products/PloneBooking/LICENSE
Products/PloneBooking/README.txt
Products/PloneBooking/TESTED_WITH
Products/PloneBooking/__init__.py
Products/PloneBooking/config.py
Products/PloneBooking/configure.zcml
Products/PloneBooking/interfaces.py
Products/PloneBooking/product.txt
Products/PloneBooking/refresh.txt
Products/PloneBooking/tool.gif
Products/PloneBooking/version.txt
Products/PloneBooking/Extensions/Install.py
Products/PloneBooking/Extensions/__init__.py
Products/PloneBooking/Extensions/migratebookables.py
Products/PloneBooking/browser/__init__.py
Products/PloneBooking/browser/configure.zcml
Products/PloneBooking/browser/export.py
Products/PloneBooking/browser/filter.py
Products/PloneBooking/browser/templates/export_form.pt
Products/PloneBooking/browser/templates/filter_select_options.pt
Products/PloneBooking/content/BookableObject.py
Products/PloneBooking/content/Booking.py
Products/PloneBooking/content/BookingCenter.py
Products/PloneBooking/content/__init__.py
Products/PloneBooking/content/schemata.py
Products/PloneBooking/content/vocabulary.py
Products/PloneBooking/doc/FAQ
Products/PloneBooking/doc/README.txt
Products/PloneBooking/doc/SCREENSHOTS
Products/PloneBooking/doc/calendar_day.png
Products/PloneBooking/doc/calendar_month.png
Products/PloneBooking/doc/calendar_week.png
Products/PloneBooking/doc/icon.png
Products/PloneBooking/doc/listing.png
Products/PloneBooking/i18n/plonebooking-cs.po
Products/PloneBooking/i18n/plonebooking-de.po
Products/PloneBooking/i18n/plonebooking.pot
Products/PloneBooking/i18n/plonebooking_da.po
Products/PloneBooking/i18n/plonebooking_en.po
Products/PloneBooking/i18n/plonebooking_fr.po
Products/PloneBooking/i18n/plonebooking_it.po
Products/PloneBooking/i18n/plonebooking_nl.po
