Metadata-Version: 1.0
Name: Products.PloneBooking
Version: 2.2.3
Summary: A booking center for Plone
Home-page: http://alterway.fr
Author: Alter Way Solutions
Author-email: support@ingeniweb.com
License: GPL
Keywords: plone zope booking
Platform: UNKNOWN
Classifier: Framework :: Plone
Classifier: Programming Language :: Python
Classifier: Topic :: Software Development :: Libraries :: Python Modules
